setuz/__init__.py
setuz/settings.py
setuz/setuz.py
setuz/exceptions/__init__.py
setuz/exceptions/auth_error.py
setuz/parsers/__init__.py
setuz/parsers/brand.py
setuz/parsers/measurement.py
setuz/parsers/order.py
setuz/schemes/__init__.py
setuz/schemes/base_schema.py
setuz/schemes/brand.py
setuz/schemes/measurement.py
setuz/schemes/order.py
setuz/schemes/product.py
setuz-1.0.3.dist-info/LICENSE
setuz-1.0.3.dist-info/METADATA
setuz-1.0.3.dist-info/WHEEL
setuz-1.0.3.dist-info/top_level.txt
setuz-1.0.3.dist-info/RECORD
