Metadata-Version: 2.1
Name: setuz
Version: 1.0.3
Summary: SetUz
Home-page: https://github.com/set-uz/setuz
Author: Sadullayev Bekhzod
Author-email: begymrx@gmail.com
License: UNKNOWN
Platform: UNKNOWN
Classifier: Programming Language :: Python :: 3
Classifier: License :: OSI Approved :: MIT License
Requires-Python: >=3.5
Requires-Dist: requests
